hypatie/__init__.py
hypatie/animation.py
hypatie/catalogues.py
hypatie/coordinates.py
hypatie/cosmology.py
hypatie/earth.py
hypatie/horizons.py
hypatie/iau.py
hypatie/plots.py
hypatie/simbad.py
hypatie/solar_system.py
hypatie/time.py
hypatie/transform.py
hypatie/utils.py
hypatie/data/__init__.py
hypatie/data/cities.py
hypatie/data/major_bodies.py
hypatie/data/simbad_bright_objects.py
hypatie/data/simbad_otypes.py
hypatie-2.20.2.dist-info/LICENSE.txt
hypatie-2.20.2.dist-info/METADATA
hypatie-2.20.2.dist-info/WHEEL
hypatie-2.20.2.dist-info/top_level.txt
hypatie-2.20.2.dist-info/RECORD
