Metadata-Version: 2.1
Name: hypatie
Version: 2.20.2
Summary: A python package for astronomical calculations
Home-page: https://github.com/behrouzz/hypatie
Author: Behrouz Safari
Author-email: behrouz.safari@gmail.com
License: MIT
Classifier: Programming Language :: Python :: 3
Classifier: License :: OSI Approved :: MIT License
Classifier: Operating System :: OS Independent
Requires-Python: >=3.6
License-File: LICENSE.txt
Requires-Dist: numpy
Requires-Dist: scipy
Requires-Dist: matplotlib
Requires-Dist: pandas
Requires-Dist: requests
